pandas_validity/__init__.py
pandas_validity/abstract.py
pandas_validity/custom_typings.py
pandas_validity/data_type_registry.py
pandas_validity/exceptions.py
pandas_validity/py.typed
pandas_validity/validator.py
pandas_validity-0.1.1.dist-info/LICENSE
pandas_validity-0.1.1.dist-info/METADATA
pandas_validity-0.1.1.dist-info/WHEEL
pandas_validity-0.1.1.dist-info/RECORD
