Metadata-Version: 2.1
Name: pandas-validity
Version: 0.1.1
Summary: Validation library for Pandas Dataframe
Home-page: https://github.com/ohmycoffe/pandas-validity
License: MIT
Keywords: pandas,dataframe,validation
Author: ohmycoffe
Author-email: ohmycoffe1@gmail.com
Requires-Python: >=3.9,<4.0
Classifier: Development Status :: 3 - Alpha
Classifier: Environment :: Console
Classifier: Intended Audience :: Developers
Classifier: Intended Audience :: Science/Research
Classifier: License :: OSI Approved :: MIT License
Classifier: Operating System :: OS Independent
Classifier: Programming Language :: Python
Classifier: Programming Language :: Python :: 3
Classifier: Programming Language :: Python :: 3.9
Classifier: Programming Language :: Python :: 3.10
Classifier: Programming Language :: Python :: 3.11
Classifier: Topic :: Software Development :: Libraries
Requires-Dist: exceptiongroup (>=1.1.3,<2.0.0)
Requires-Dist: pandas (>=2.0.3,<3.0.0)
Project-URL: Repository, https://github.com/ohmycoffe/pandas-validity
